nuage_metroae_config/__init__.py
nuage_metroae_config/actions.py
nuage_metroae_config/bambou_adapter.py
nuage_metroae_config/configuration.py
nuage_metroae_config/device_reader_base.py
nuage_metroae_config/device_writer_base.py
nuage_metroae_config/document_template_md.py
nuage_metroae_config/errors.py
nuage_metroae_config/es_reader.py
nuage_metroae_config/logger.py
nuage_metroae_config/query.py
nuage_metroae_config/template.py
nuage_metroae_config/user_data_parser.py
nuage_metroae_config/util.py
nuage_metroae_config/variable_reader.py
nuage_metroae_config/vsd_writer.py
nuage_metroae_config-1.1.0.dist-info/LICENSE
nuage_metroae_config-1.1.0.dist-info/METADATA
nuage_metroae_config-1.1.0.dist-info/WHEEL
nuage_metroae_config-1.1.0.dist-info/top_level.txt
nuage_metroae_config-1.1.0.dist-info/RECORD
