Metadata-Version: 2.1
Name: nuage-metroae-config
Version: 1.1.0
Summary: Template-based configuration tool for Nuage Networks VSD
Home-page: https://github.com/nuagenetworks/nuage-metroae-config
Author: Nuage Devops
Author-email: devops@nuagenetworks.net
License: UNKNOWN
Platform: UNKNOWN
Classifier: Programming Language :: Python :: 2
Classifier: Programming Language :: Python :: 3
Classifier: License :: OSI Approved :: Apache Software License
Classifier: Operating System :: OS Independent
Requires-Python: >=2.7
Requires-Dist: bambou
Requires-Dist: Jinja2
Requires-Dist: lark-parser
Requires-Dist: PyYAML
